bioTea/__init__.py
bioTea/__main__.py
bioTea/classes.py
bioTea/cli.py
bioTea/docker_wrapper.py
bioTea/pour.py
bioTea/wizard.py
bioTea/resources/__init__.py
bioTea/resources/bioTEA_run_default_options.yaml
bioTea/resources/default_options.yml
bioTea/utils/__init__.py
bioTea/utils/errors.py
bioTea/utils/path_checker.py
bioTea/utils/strings.py
bioTea/utils/tools.py
bioTea/utils/xml_parser.py
tests/__init__.py
tests/test_integration.py
tests/test_tools.py
bioTEA-2.0.0.dist-info/LICENSE
bioTEA-2.0.0.dist-info/METADATA
bioTEA-2.0.0.dist-info/WHEEL
bioTEA-2.0.0.dist-info/entry_points.txt
bioTEA-2.0.0.dist-info/top_level.txt
bioTEA-2.0.0.dist-info/RECORD
